sinaSearchTools/__init__.py
sinaSearchTools/tools.py
sinaSearchTools-6.4.0.dist-info/METADATA
sinaSearchTools-6.4.0.dist-info/WHEEL
sinaSearchTools-6.4.0.dist-info/top_level.txt
sinaSearchTools-6.4.0.dist-info/RECORD
